MANIFEST.in
README.rst
README.txt
setup.py
bin/flowhub
flowhub/__init__.py
flowhub/configurator.py
flowhub/core.py
flowhub/decorators.py
flowhub/engine.py
flowhub.egg-info/PKG-INFO
flowhub.egg-info/SOURCES.txt
flowhub.egg-info/dependency_links.txt
flowhub.egg-info/requires.txt
flowhub.egg-info/top_level.txt
flowhub/managers/__init__.py
flowhub/managers/feature.py
flowhub/managers/hotfix.py
flowhub/managers/pull_request.py
flowhub/managers/release.py
tests/test_configurator.py
tests/test_core.py
tests/test_engine.py
tests/managers/test_features.py