Metadata-Version: 1.0
Name: flowhub
Version: 0.6.1
Summary: Git-flow adapted for GitHub
Home-page: http://github.com/haaksmash/flowhub
Author: Haak Saxberg
Author-email: haak.erling@gmail.com
License: UNKNOWN
Platform: UNKNOWN
